pgdancer/__init__.py
pgdancer/cmdline.py
pgdancer/core.py
pgdancer/core_settings.py
pgdancer/histogram.py
pgdancer/settings.py
pgdancer/images/green_start.png
pgdancer/images/icon.png
pgdancer/images/red_start.png
pgdancer-0.1.dist-info/METADATA
pgdancer-0.1.dist-info/RECORD
pgdancer-0.1.dist-info/WHEEL
pgdancer-0.1.dist-info/entry_points.txt
pgdancer-0.1.dist-info/top_level.txt
