Metadata-Version: 2.1
Name: pgdancer
Version: 0.1
Summary: common dynamic data visualization framework for python
Home-page: https://github.com/zgmphoo/pgdancer
Author: zgmphoo
Author-email: zgmphoo@gmail.com
License: BSD License
Platform: any
Classifier: Operating System :: OS Independent
Classifier: License :: OSI Approved :: BSD License
Classifier: Programming Language :: Python :: 3.6
Classifier: Programming Language :: Python :: 3.7
Requires-Dist: pandas (>=0.20.1)
Requires-Dist: pygame (>=1.9.5)
